rtl/mac_pipelined.sv
module mac_pipelined #(
    parameter WIDTH = 8
)(
    input  logic                 clk,
    input  logic                 rst,

    input  logic [WIDTH-1:0]     a,
    input  logic [WIDTH-1:0]     b,
    input  logic [2*WIDTH-1:0]   acc,

    output logic [2*WIDTH-1:0]   result
);

    // ------------------------------------------------
    // Pipeline Stage 1
    // Multiply A and B
    // ------------------------------------------------

    logic [2*WIDTH-1:0] product_reg;
    logic [2*WIDTH-1:0] acc_reg;

    always_ff @(posedge clk) begin
        if (rst) begin
            product_reg <= '0;
            acc_reg     <= '0;
        end
        else begin
            product_reg <= a * b;
            acc_reg     <= acc;
        end
    end

    // ------------------------------------------------
    // Pipeline Stage 2
    // Add product and accumulated value
    // ------------------------------------------------

    always_ff @(posedge clk) begin
        if (rst) begin
            result <= '0;
        end
        else begin
            result <= product_reg + acc_reg;
        end
    end

endmodule

tb/mac_pipelined_tb.sv
`timescale 1ns/1ps

module mac_pipelined_tb;

    parameter WIDTH = 8;

    logic clk;
    logic rst;

    logic [WIDTH-1:0] a;
    logic [WIDTH-1:0] b;
    logic [2*WIDTH-1:0] acc;

    logic [2*WIDTH-1:0] result;

    mac_pipelined #(
        .WIDTH(WIDTH)
    ) dut (
        .clk(clk),
        .rst(rst),
        .a(a),
        .b(b),
        .acc(acc),
        .result(result)
    );

    // Clock: 10 ns period
    initial begin
        clk = 0;
        forever #5 clk = ~clk;
    end

    // Test procedure
    task automatic test_mac(
        input integer test_a,
        input integer test_b,
        input integer test_acc
    );

        integer expected;

        begin
            expected = (test_a * test_b) + test_acc;

            // Drive inputs away from rising edge
            @(negedge clk);

            a   = test_a;
            b   = test_b;
            acc = test_acc;

            // Stage 1: multiplication is captured
            @(posedge clk);

            // Stage 2: addition/result is captured
            @(posedge clk);

            #1;

            if (result == expected) begin
                $display(
                    "TEST PASSED: %0d x %0d + %0d = %0d",
                    test_a, test_b, test_acc, result
                );
            end
            else begin
                $display(
                    "TEST FAILED: %0d x %0d + %0d | Expected=%0d Got=%0d",
                    test_a, test_b, test_acc, expected, result
                );
            end
        end

    endtask

    initial begin

        $dumpfile("mac_pipelined.vcd");
        $dumpvars(0, mac_pipelined_tb);

        // Initial values
        a   = 0;
        b   = 0;
        acc = 0;

        // Reset
        rst = 1;

        repeat (2)
            @(posedge clk);

        #1;
        rst = 0;

        // --------------------------------
        // Directed Tests
        // --------------------------------

        test_mac(5, 4, 10);

        test_mac(10, 3, 20);

        test_mac(15, 15, 5);

        test_mac(0, 100, 25);

        test_mac(25, 8, 50);

        test_mac(255, 255, 100);

        // --------------------------------
        // Complete
        // --------------------------------

        $display("--------------------------------");
        $display("PIPELINED MAC SIMULATION COMPLETE");
        $display("--------------------------------");

        $finish;

    end

endmodule

mac_pipelined.vcd
$date
	Fri Sep 11 12:24:59 2026
$end
$version
	Icarus Verilog
$end
$timescale
	1ps
$end
$scope module mac_pipelined_tb $end
$var wire 16 ! result [15:0] $end
$var parameter 32 " WIDTH $end
$var reg 8 # a [7:0] $end
$var reg 16 $ acc [15:0] $end
$var reg 8 % b [7:0] $end
$var reg 1 & clk $end
$var reg 1 ' rst $end
$scope module dut $end
$var wire 8 ( a [7:0] $end
$var wire 16 ) acc [15:0] $end
$var wire 8 * b [7:0] $end
$var wire 1 & clk $end
$var wire 1 ' rst $end
$var parameter 32 + WIDTH $end
$var reg 16 , acc_reg [15:0] $end
$var reg 16 - product_reg [15:0] $end
$var reg 16 . result [15:0] $end
$upscope $end
$scope task test_mac $end
$upscope $end
$upscope $end
$enddefinitions $end
$comment Show the parameter values. $end
$dumpall
b1000 +
b1000 "
$end
#0
$dumpvars
bx .
bx -
bx ,
b0 *
b0 )
b0 (
1'
0&
b0 %
b0 $
b0 #
bx !
$end
#5000
b0 ,
b0 -
b0 !
b0 .
1&
#10000
0&
#15000
1&
#16000
0'
#20000
b1010 $
b1010 )
b100 %
b100 *
b101 #
b101 (
0&
#25000
b1010 ,
b10100 -
1&
#30000
0&
#35000
b11110 !
b11110 .
1&
#40000
b10100 $
b10100 )
b11 %
b11 *
b1010 #
b1010 (
0&
#45000
b10100 ,
b11110 -
1&
#50000
0&
#55000
b110010 !
b110010 .
1&
#60000
b101 $
b101 )
b1111 %
b1111 *
b1111 #
b1111 (
0&
#65000
b101 ,
b11100001 -
1&
#70000
0&
#75000
b11100110 !
b11100110 .
1&
#80000
b11001 $
b11001 )
b1100100 %
b1100100 *
b0 #
b0 (
0&
#85000
b11001 ,
b0 -
1&
#90000
0&
#95000
b11001 !
b11001 .
1&
#100000
b110010 $
b110010 )
b1000 %
b1000 *
b11001 #
b11001 (
0&
#105000
b110010 ,
b11001000 -
1&
#110000
0&
#115000
b11111010 !
b11111010 .
1&
#120000
b1100100 $
b1100100 )
b11111111 %
b11111111 *
b11111111 #
b11111111 (
0&
#125000
b1100100 ,
b1111111000000001 -
1&
#130000
0&
#135000
b1111111001100101 !
b1111111001100101 .
1&
